auth_checker/__init__.py
auth_checker/rbac_model.conf
auth_checker/authn/__init__.py
auth_checker/authn/routes.py
auth_checker/authz/__init__.py
auth_checker/authz/authorizer.py
auth_checker/authz/routes.py
auth_checker/models/__init__.py
auth_checker/models/models.py
auth_checker/plugins/__init__.py
auth_checker/plugins/authorize/__init__.py
auth_checker/plugins/authorize/casbin_pl.py
auth_checker/plugins/authorize/satauth_pl.py
auth_checker/tests/__init__.py
auth_checker/tests/conftest.py
auth_checker/tests/test_models.py
auth_checker/tests/test_policy.csv
auth_checker/tests/test_routes.py
auth_checker/util/__init__.py
auth_checker/util/authn_types.py
auth_checker/util/authorization_roles.py
auth_checker/util/interfaces.py
auth_checker/util/settings.py
auth_checker-2.1.1.dist-info/LICENSE
auth_checker-2.1.1.dist-info/WHEEL
auth_checker-2.1.1.dist-info/METADATA
auth_checker-2.1.1.dist-info/RECORD
