Metadata-Version: 2.1
Name: auth-checker
Version: 2.1.1
Summary: Contains the AuthChecker class for apps using the Auth Service
Author-email: Ryan Semmler <rsemmle@ncsu.edu>, Luc Sanchez <lgsanche@ncsu.edu>, Jeremy Gibson <jmgibso3@ncsu.edu>
Requires-Python: >=3.9
Classifier: Programming Language :: Python :: 3
Classifier: License :: OSI Approved :: MIT License
Classifier: Operating System :: OS Independent
Requires-Dist: fastapi==0.110.2
Requires-Dist: pyjwt==2.8.0
Requires-Dist: casbin==1.36.0
Requires-Dist: google-auth==2.19.1
Requires-Dist: casbin_redis_adapter==1.2.0
Requires-Dist: casbin_pymongo_adapter==1.1.0
Requires-Dist: sat-utils==1.7.0
Requires-Dist: casbin_sqlalchemy_adapter==1.4.0 ; extra == "casbinsql"
Requires-Dist: pytest==8.2.2 ; extra == "dev"
Requires-Dist: pytest-cov==4.1.0 ; extra == "dev"
Requires-Dist: pytest-mock>=3.14.0, <4.0.0 ; extra == "dev"
Requires-Dist: pytest-env>=1.1.3, <1.2.0 ; extra == "dev"
Requires-Dist: coverage[toml]>=6.2 ; extra == "dev"
Requires-Dist: black>=23.3.0, <24.0.0 ; extra == "dev"
Requires-Dist: ruff==0.1.1 ; extra == "dev"
Requires-Dist: bandit>=1.7.4, <2.0.0 ; extra == "dev"
Requires-Dist: bandit[toml]>=1.7.4, <2.0.0 ; extra == "dev"
Requires-Dist: pre-commit>=2.16.0, <3.0.0 ; extra == "dev"
Requires-Dist: isort>=5.10.1, <6.0.0 ; extra == "dev"
Requires-Dist: pyupgrade>=2.29.1, <3.0.0 ; extra == "dev"
Requires-Dist: flit>=3.8.0, <4.0.0 ; extra == "dev"
Requires-Dist: httpx>=0.27.0, <1.0.0 ; extra == "dev"
Requires-Dist: jupyterlab>=4.1.5, <5.0.0 ; extra == "dev"
Project-URL: Homepage, https://github.com/ncstate-sat/auth_checker
Provides-Extra: casbinsql
Provides-Extra: dev
